{"text": " Deber\u00edamos visitar el Museo Este fin de semana.", "segments": [{"start": 0.18, "end": 3.2, "text": " Deber\u00edamos visitar el Museo Este fin de semana.", "seek": 0.0, "tokens": [1346, 607, 16275, 3441, 289, 806, 47293, 78, 16105, 962, 368, 20205, 13], "temperature": 0.0, "avg_logprob": -0.3933998942375183, "compression_ratio": 0.8571428571428571, "no_speech_prob": 0.006902138236910105, "words": [{"word": " Deber\u00edamos", "start": 0.18, "end": 0.68, "probability": 0.66566215789256, "tokens": [1346, 607, 16275], "segment_id": 0, "id": 0}, {"word": " visitar", "start": 0.68, "end": 1.36, "probability": 0.9921474456787109, "tokens": [3441, 289], "segment_id": 0, "id": 1}, {"word": " el", "start": 1.36, "end": 1.52, "probability": 0.9882006645202637, "tokens": [806], "segment_id": 0, "id": 2}, {"word": " Museo", "start": 1.52, "end": 2.06, "probability": 0.8300800621509552, "tokens": [47293, 78], "segment_id": 0, "id": 3}, {"word": " Este", "start": 2.06, "end": 2.4, "probability": 0.5290193557739258, "tokens": [16105], "segment_id": 0, "id": 4}, {"word": " fin", "start": 2.4, "end": 2.68, "probability": 0.349216490983963, "tokens": [962], "segment_id": 0, "id": 5}, {"word": " de", "start": 2.68, "end": 2.84, "probability": 0.9988007545471191, "tokens": [368], "segment_id": 0, "id": 6}, {"word": " semana.", "start": 2.84, "end": 3.2, "probability": 0.9516775012016296, "tokens": [20205, 13], "segment_id": 0, "id": 7}], "id": 0}], "language": "es", "ori_dict": {"text": " Deber\u00edamos visitar el Museo Este fin de semana.", "segments": [{"id": 0, "start": 0.18, "end": 3.2, "text": " Deber\u00edamos visitar el Museo Este fin de semana.", "seek": 0.0, "tokens": [1346, 607, 16275, 3441, 289, 806, 47293, 78, 16105, 962, 368, 20205, 13], "temperature": 0.0, "avg_logprob": -0.3933998942375183, "compression_ratio": 0.8571428571428571, "no_speech_prob": 0.006902138236910105, "words": [{"word": " Deber\u00edamos", "start": 0.18, "end": 0.68, "probability": 0.66566215789256, "tokens": [1346, 607, 16275], "segment_id": null, "id": null}, {"word": " visitar", "start": 0.68, "end": 1.36, "probability": 0.9921474456787109, "tokens": [3441, 289], "segment_id": null, "id": null}, {"word": " el", "start": 1.36, "end": 1.52, "probability": 0.9882006645202637, "tokens": [806], "segment_id": null, "id": null}, {"word": " Museo", "start": 1.52, "end": 2.06, "probability": 0.8300800621509552, "tokens": [47293, 78], "segment_id": null, "id": null}, {"word": " Este", "start": 2.06, "end": 2.4, "probability": 0.5290193557739258, "tokens": [16105], "segment_id": null, "id": null}, {"word": " fin", "start": 2.4, "end": 2.68, "probability": 0.349216490983963, "tokens": [962], "segment_id": null, "id": null}, {"word": " de", "start": 2.68, "end": 2.84, "probability": 0.9988007545471191, "tokens": [368], "segment_id": null, "id": null}, {"word": " semana.", "start": 2.84, "end": 3.2, "probability": 0.9516775012016296, "tokens": [20205, 13], "segment_id": null, "id": null}]}], "language": "es", "time_scale": null}}